{
  "id": "1921b40d-4a9a-4949-ab02-af517c75531f",
  "prevId": "d2c6d58b-ff92-4c3e-892d-c890954e3eb5",
  "version": "7",
  "dialect": "postgresql",
  "tables": {
    "public.goal_completions": {
      "name": "goal_completions",
      "schema": "",
      "columns": {
        "id": {
          "name": "id",
          "type": "text",
          "primaryKey": true,
          "notNull": true
        },
        "goal_id": {
          "name": "goal_id",
          "type": "text",
          "primaryKey": false,
          "notNull": true
        },
        "created_at": {
          "name": "created_at",
          "type": "timestamp with time zone",
          "primaryKey": false,
          "notNull": true,
          "default": "now()"
        }
      },
      "indexes": {},
      "foreignKeys": {
        "goal_completions_goal_id_goals_íd_fk": {
          "name": "goal_completions_goal_id_goals_íd_fk",
          "tableFrom": "goal_completions",
          "tableTo": "goals",
          "columnsFrom": [
            "goal_id"
          ],
          "columnsTo": [
            "íd"
          ],
          "onDelete": "no action",
          "onUpdate": "no action"
        }
      },
      "compositePrimaryKeys": {},
      "uniqueConstraints": {}
    },
    "public.goals": {
      "name": "goals",
      "schema": "",
      "columns": {
        "íd": {
          "name": "íd",
          "type": "text",
          "primaryKey": true,
          "notNull": true
        },
        "title": {
          "name": "title",
          "type": "text",
          "primaryKey": false,
          "notNull": true
        },
        "desired_weekly_frequency": {
          "name": "desired_weekly_frequency",
          "type": "integer",
          "primaryKey": false,
          "notNull": true
        },
        "created_at": {
          "name": "created_at",
          "type": "timestamp with time zone",
          "primaryKey": false,
          "notNull": true,
          "default": "now()"
        }
      },
      "indexes": {},
      "foreignKeys": {},
      "compositePrimaryKeys": {},
      "uniqueConstraints": {}
    }
  },
  "enums": {},
  "schemas": {},
  "sequences": {},
  "_meta": {
    "columns": {},
    "schemas": {},
    "tables": {}
  }
}